rankereval/__init__.py
rankereval/data.py
rankereval/metrics.py
rankerEval-0.2.0.dist-info/LICENSE
rankerEval-0.2.0.dist-info/METADATA
rankerEval-0.2.0.dist-info/WHEEL
rankerEval-0.2.0.dist-info/top_level.txt
rankerEval-0.2.0.dist-info/RECORD
