Metadata-Version: 2.1
Name: rankerEval
Version: 0.2.0
Summary: A fast implementation of ranking metrics for information retrieval and recommendation.
Home-page: https://github.com/microsoft/rankerEval
Author: Tobias Schnabel
Author-email: tobias.schnabel@microsoft.com
License: MIT
Keywords: ranking recommendation evaluation map mrr
Platform: UNKNOWN
Classifier: Development Status :: 4 - Beta
Classifier: License :: OSI Approved :: MIT License
Classifier: Programming Language :: Python
Classifier: Programming Language :: Python :: 3
Classifier: Programming Language :: Python :: 3.6
Classifier: Programming Language :: Python :: 3.7
Classifier: Programming Language :: Python :: 3.8
Requires-Python: >=3.6
Requires-Dist: numpy (>=1.18)
Requires-Dist: numba (>=0.53.0)
Requires-Dist: scipy (>=1.0)
